pydlfmt/__init__.py
pydlfmt-0.0.12.dist-info/LICENSE
pydlfmt-0.0.12.dist-info/METADATA
pydlfmt-0.0.12.dist-info/WHEEL
pydlfmt-0.0.12.dist-info/top_level.txt
pydlfmt-0.0.12.dist-info/RECORD
