Metadata-Version: 2.1
Name: pydlfmt
Version: 0.0.12
Summary: pydlfmt will take a list of objects, dicts, etc and output them to a PDF or XLSX
Home-page: https://github.com/jpsteil/pydlfmt
Author: Jim Steil
Author-email: jim@steilonline.com
Classifier: Programming Language :: Python :: 3
Classifier: License :: OSI Approved :: Apache Software License
Classifier: Operating System :: OS Independent
Requires-Python: >=3.7
License-File: LICENSE
Requires-Dist: pytest
Requires-Dist: reportlab
Requires-Dist: xlsxwriter
